pycryptools/__init__.py
pycryptools/alberti.py
pycryptools/atbash.py
pycryptools/caesar.py
pycryptools/command.py
pycryptools/jefferson.py
pycryptools/letter_number.py
pycryptools/morse.py
pycryptools/polybios.py
pycryptools/scytale.py
pycryptools/vigenere.py
pycryptools-2.0.1.dist-info/LICENSE
pycryptools-2.0.1.dist-info/METADATA
pycryptools-2.0.1.dist-info/WHEEL
pycryptools-2.0.1.dist-info/entry_points.txt
pycryptools-2.0.1.dist-info/top_level.txt
pycryptools-2.0.1.dist-info/RECORD
