Metadata-Version: 2.1
Name: pycryptools
Version: 2.0.1
Summary: PyCrypTools is a python library that brings us a series of classics algorithms to encrypt and decrypt inputs.
Home-page: https://pypi.org/project/pycryptools/
Author: Carlos Padilla
Author-email: cpadlab@gmail.com
License: CC0-1.0 License
Project-URL: Source Code, https://github.com/14wual/pycryptools/
Project-URL: Bug Tracker, https://github.com/14wual/pycryptools/issues
Project-URL: Documentation, https://pycryptools.readthedocs.io/
Keywords: encrypt decrypt
Classifier: Development Status :: 4 - Beta
Classifier: Programming Language :: Python :: 3
Classifier: License :: OSI Approved :: Apache Software License
Classifier: Operating System :: OS Independent
License-File: LICENSE
